LICENSE
MANIFEST.in
README.rst
setup.py
pytest_beds.egg-info/PKG-INFO
pytest_beds.egg-info/SOURCES.txt
pytest_beds.egg-info/dependency_links.txt
pytest_beds.egg-info/entry_points.txt
pytest_beds.egg-info/not-zip-safe
pytest_beds.egg-info/requires.txt
pytest_beds.egg-info/top_level.txt
testbeds/__init__.py
testbeds/fixtures.py
testbeds/plugin.py
testbeds/taskqueue_stub.py